Workbook

Sheet Read me
A1: TUTOR test suite
A2: Generated 2026-09-29 by backend/qa/build_test_suite.py
A3: Summary
A4: Manual cases | B4: =COUNTA('Manual cases'!$A$2:$A$96) -> 95 | C4: Written in docs/testing/test-cases/*.md
A5: Priority P1 | B5: =COUNTIF('Manual cases'!$E$2:$E$96,"P1") -> 64 | C5: Must pass before any release
A6: Priority P2 | B6: =COUNTIF('Manual cases'!$E$2:$E$96,"P2") -> 26
A7: Priority P3 | B7: =COUNTIF('Manual cases'!$E$2:$E$96,"P3") -> 5
A8: With automated coverage | B8: =COUNTIF('Manual cases'!$K$2:$K$96,">0") -> 84 | C8: Automated tests exist too
A9: Automated coverage % | B9: =IF(B4=0,0,B8/B4) -> 0.88421053 | C9: Share of manual cases also covered by automation
A10: Status: Pass | B10: =COUNTIF('Manual cases'!$N$2:$N$96,"Pass") -> 0 | C10: Filled in by testers in 'Manual cases'
A11: Status: Fail | B11: =COUNTIF('Manual cases'!$N$2:$N$96,"Fail") -> 0 | C11: Every Fail needs a Bug ID
A12: Status: Blocked | B12: =COUNTIF('Manual cases'!$N$2:$N$96,"Blocked") -> 0 | C12: Can't be run (environment, missing feature)
A13: Status: Not run | B13: =COUNTIF('Manual cases'!$N$2:$N$96,"Not run") -> 95
A14: Pass rate (of cases run) | B14: =IF((B10+B11+B12)=0,0,B10/(B10+B11+B12)) -> 0 | C14: Pass ÷ (Pass + Fail + Blocked)
A15: Automated tests | B15: =COUNTA('Automated tests'!$A$2:$A$186) -> 185 | C15: Django tests; run by ./dev.sh and CI
A16: Smoke checks | B16: =COUNTA('Smoke checks'!$A$2:$A$43) -> 42 | C16: Black-box checks over HTTP
A17: Requirements without a manual case | B17: =COUNTIF(Traceability!$H$2:$H$45,"No manual case") -> 15 | C17: Planned features show here until they are built
A19: How to use
A20: 1 | C20: Filter 'Manual cases' by Area or Priority, put your name in Assignee (yellow cells are yours to fill).
A21: 2 | C21: Run the case exactly as written. Accounts are in 'Demo accounts' and docs/testing/demo-data.md.
A22: 3 | C22: Set Status, Tested on and Build / commit. For every Fail, add a row in 'Bug log' and put its ID in Bug ID.
A23: 4 | C23: Don't edit case text here: change docs/testing/test-cases/*.md in a pull request, then rebuild.
A24: Statuses | C24: Not run · Pass · Fail · Blocked · N/A
A25: Environments | C25: Local = your machine with tester tools (dev outbox). Hosted = https://tutor-platform-ovlg.onrender.com
A26: Severity | C26: Critical: data leak, security or consent bypass · High: a P1 case fails · Medium: a P2 case fails · Low: cosmetic
A27: Rebuild | C27: From backend/: python qa/build_test_suite.py (also validates the automation map)

Sheet Manual cases
A1: ID | B1: Area | C1: Section | D1: Title | E1: Priority | F1: Requirements | G1: Environment | H1: Preconditions / accounts | I1: Steps | J1: Expected result | K1: Automated tests | L1: Automated by | M1: Assignee | N1: Status | O1: Tested on | P1: Build / commit | Q1: Bug ID | R1: Notes
A2: TC-SET-1 | B2: Accounts & consent | C2: Setup | D2: Health check | E2: P1 | F2: NFR-AVAIL-1 | G2: Local | I2: `GET /health`. | J2: `200 {"ok": true, "db": true}`. | K2: 3 | L2: apps.accounts.tests.HealthTests.test_health apps.accounts.tests.HealthTests.test_health_is_503_when_the_database_is_unreachable hosted:H1 | N2: Not run
A3: TC-SET-2 | B3: Accounts & consent | C3: Setup | D3: Smoke test passes | E3: P1 | G3: Local | I3: run `python qa/smoke_test.py`. | J3: every line `PASS`, last line `N/N checks passed`. | K3: 1 | L3: smoke:S0 | N3: Not run
A4: TC-SET-3 | B4: Accounts & consent | C4: Setup | D4: Logged-in POST works from the docs page | E4: P1 | F4: NFR-SEC-2 | G4: Local | H4: logged in as `student_enrolled` via `POST /auth/login` in the docs page, then page reloaded (Ctrl+F5). | I4: `POST /lessons/{id}/finish` for any AI Foundations lesson. | J4: `200`. A `403` mentioning CSRF is a High bug. | K4: 1 | L4: apps.accounts.test_api.SecureByDefaultTests.test_docs_page_sends_csrf_token | N4: Not run
A5: TC-ACC-01 | B5: Accounts & consent | C5: Sign-up and login | D5: Student sign-up | E5: P1 | F5: FR-ACC-1, FR-ACC-4 | G5: Local | I5: `POST /auth/signup/student` with name, mobile `98xxxxxxxx` (new), password, `class_number: 8`, `board_code: "CBSE"`, city, `parent_contact` (another new mobile). | J5: `201`; `mobile` returned as `+9198…`; `student.status = "awaiting_consent"`; outbox for the parent has an `/approve/<token>` link; outbox for the student has a 6-digit code. | K5: 2 | L5: apps.accounts.test_api.SignupAndApprovalFlow.test_student_signup_waits_for_parent smoke:A1 | N5: Not run
A6: TC-ACC-02 | B6: Accounts & consent | C6: Sign-up and login | D6: Parent sign-up and contact verification | E6: P1 | F6: FR-ACC-2 | G6: Local | I6: `POST /auth/signup/parent`; read the code from the outbox; `POST /auth/otp/verify` with `purpose: "verify_contact"`. | J6: `201` then `200` with `mobile_verified: true`. | K6: 2 | L6: apps.accounts.test_api.SignupAndApprovalFlow.test_full_approval smoke:A5 | N6: Not run
A7: TC-ACC-03 | B7: Accounts & consent | C7: Sign-up and login | D7: Duplicate sign-up refused | E7: P1 | F7: FR-ACC-1 | G7: Local | I7: repeat TC-ACC-01 with the same mobile. | J7: `409`, `code: "already_registered"`. | K7: 1 | L7: apps.accounts.test_api.LoginAndErrors.test_duplicate_signup | N7: Not run
A8: TC-ACC-04 | B8: Accounts & consent | C8: Sign-up and login | D8: Validation errors | E8: P2 | F8: FR-ACC-1 | G8: Local | I8: sign up with (a) no email and no mobile, (b) `class_number: 13`, (c) `board_code: "XYZ"`, (d) password `12345678`, (e) parent contact equal to the student's own. | J8: `400`, `code: "validation_error"`, the offending field named in `fields` (or `non_field` for (a)). | K8: 1 | L8: apps.accounts.test_api.LoginAndErrors.test_validation_error_format | N8: Not run
A9: TC-ACC-05 | B9: Accounts & consent | C9: Sign-up and login | D9: Login with email, 10-digit mobile and +91 mobile | E9: P1 | F9: FR-ACC-1 | G9: Local | I9: `POST /auth/login` as `student_enrolled` using `esha@test.tutor`, `9000000003` and `+919000000003`. | J9: `200` each time; `GET /me` returns Esha. | K9: 3 | L9: apps.accounts.test_api.LoginAndErrors.test_login_with_plain_10_digit_mobile apps.accounts.tests.LoginTests.test_login_with_email apps.accounts.tests.LoginTests.test_login_with_mobile | N9: Not run
A10: TC-ACC-06 | B10: Accounts & consent | C10: Sign-up and login | D10: Wrong password | E10: P1 | G10: Local | I10: `POST /auth/login` as `esha@test.tutor` with a wrong password, then with `nobody@test.tutor`. | J10: `400`, `code: "invalid_credentials"`; message doesn't reveal whether the account exists. | K10: 2 | L10: apps.accounts.test_api.LoginAndErrors.test_wrong_password hosted:X4 | N10: Not run
A11: TC-ACC-07 | B11: Accounts & consent | C11: Sign-up and login | D11: Logout | E11: P2 | G11: Local | I11: `POST /auth/logout`, then `GET /me`. | J11: `200`, then `401 not_authenticated`. | K11: 0 | N11: Not run
A12: TC-ACC-08 | B12: Accounts & consent | C12: Sign-up and login | D12: Password reset | E12: P1 | F12: FR-ACC-2 | G12: Local | I12: `POST /auth/otp/send` (`purpose: "reset_password"`) for `9000000002`; take the code from the outbox; `POST /auth/password/reset` with a new strong password; log in with it. Afterwards run `seed_test_accounts` to restore. | J12: `200`, `200`, login succeeds with the new password and fails with the old one. | K12: 1 | L12: apps.accounts.test_api.LoginAndErrors.test_password_reset | N12: Not run
A13: TC-ACC-09 | B13: Accounts & consent | C13: Sign-up and login | D13: Codes: expiry, attempts, rate limit | E13: P2 | F13: FR-ACC-2 | G13: Local | I13: (a) verify with a wrong code 5 times, then the right one; (b) request 6 codes within 10 minutes for one contact. | J13: (a) all fail with `invalid_code`, and the right code also fails after 5 wrong tries; (b) 6th request `429 limit_reached`. | K13: 1 | L13: apps.accounts.test_security.RateLimitTests.test_one_time_code_endpoints_are_rate_limited | N13: Not run
A14: TC-ACC-10 | B14: Accounts & consent | C14: Sign-up and login | D14: No code for unknown contacts | E14: P1 | F14: FR-ACC-3 | G14: Local | I14: `POST /auth/otp/send` for an unregistered number. | J14: `200` with the generic message; outbox has no message for that number. | K14: 1 | L14: apps.accounts.test_api.LoginAndErrors.test_otp_not_sent_to_unknown_contact | N14: Not run
A15: TC-CON-01 | B15: Accounts & consent | C15: Parent approval | D15: Approval link details | E15: P1 | F15: FR-ACC-4 | G15: Local | H15: TC-ACC-01 done. | I15: `GET /consent/link/<token>`. | J15: `200`: child's first name only, class label, consent text and version. | K15: 1 | L15: smoke:A6 | N15: Not run
A16: TC-CON-02 | B16: Accounts & consent | C16: Parent approval | D16: Approve | E16: P1 | F16: FR-ACC-4, FR-ACC-5 | G16: Local | H16: verified parent logged in (TC-ACC-02). | I16: `POST /consent/link/<token>/approve` `{"relationship": "mother", "accept": true}`. | J16: `200`; student's `GET /me` shows `status: "active"`; parent's `GET /me` lists the child; Admin → Consent records shows a record with text version and IP; Admin → Audit log shows `consent.given`. | K16: 3 | L16: apps.accounts.test_api.SignupAndApprovalFlow.test_full_approval smoke:A7 smoke:A8 | N16: Not run
A17: TC-CON-03 | B17: Accounts & consent | C17: Parent approval | D17: Unverified parent can't approve | E17: P1 | G17: Local | I17: new parent signs up but doesn't verify, then approves. | J17: `403 contact_not_verified`. | K17: 1 | L17: apps.accounts.test_api.SignupAndApprovalFlow.test_parent_must_verify_contact_first | N17: Not run
A18: TC-CON-04 | B18: Accounts & consent | C18: Parent approval | D18: Consent box must be ticked | E18: P2 | G18: Local | I18: approve with `accept: false`. | J18: `400 validation_error`, field `accept`. | K18: 0 | N18: Not run
A19: TC-CON-05 | B19: Accounts & consent | C19: Parent approval | D19: Link is single-use | E19: P1 | G19: Local | I19: approve twice. | J19: second call `410 link_expired`. | K19: 0 | N19: Not run
A20: TC-CON-06 | B20: Accounts & consent | C20: Parent approval | D20: "Not my child" | E20: P1 | G20: Local | I20: `POST /consent/link/<token>/report` (logged out is fine); then `GET` the link. | J20: `200`, then `410`; Admin → Approval requests shows status `reported`. | K20: 1 | L20: apps.accounts.test_api.SignupAndApprovalFlow.test_not_my_child | N20: Not run
A21: TC-CON-07 | B21: Accounts & consent | C21: Parent approval | D21: Resend limit | E21: P2 | G21: Local | H21: logged in as a waiting student. | I21: `POST /consent/requests/resend` three times. | J21: first two `200` (a new link each time; the old link stops working), third `429 limit_reached`. | K21: 1 | L21: apps.accounts.test_api.SignupAndApprovalFlow.test_resend_limit | N21: Not run
A22: TC-CON-08 | B22: Accounts & consent | C22: Parent approval | D22: Change parent contact | E22: P2 | G22: Local | I22: `PATCH /consent/requests/parent-contact` with a new email. | J22: `200`; outbox for that email has a link; the previous link returns `410`. | K22: 1 | L22: apps.accounts.test_api.SignupAndApprovalFlow.test_change_parent_contact | N22: Not run
A23: TC-CON-09 | B23: Accounts & consent | C23: Parent approval | D23: Second guardian refused (v1) | E23: P2 | F23: FR-ACC-6 | G23: Local | H23: a student already approved by parent A. | I23: a second verified parent tries to approve a new link for the same student. | J23: `409 already_has_guardian`. | K23: 1 | L23: apps.accounts.tests.GuardianConsentTests.test_only_one_active_primary_guardian | N23: Not run
A24: TC-CON-10 | B24: Accounts & consent | C24: Parent approval | D24: Parent adds a child directly | E24: P1 | G24: Local | I24: as `parent`, `POST /parent/children` with name, own email for the child, password, class 10, `ICSE`, city. | J24: `201`, status `active`; the child can log in and open a free lesson. | K24: 1 | L24: apps.accounts.test_api.ParentManagesChildren.test_add_child_withdraw_and_restore | N24: Not run
A25: TC-CON-11 | B25: Accounts & consent | C25: Parent approval | D25: Withdraw and restore consent | E25: P1 | F25: FR-ACC-7 | G25: Local | I25: as `parent`, withdraw for Asha; as Asha open a lesson; parent restores; Asha opens the lesson again. | J25: `200`; `403 consent_required`; `200`; `200`. Audit log shows `consent.withdrawn` and `consent.restored`. | K25: 5 | L25: apps.accounts.test_api.ParentManagesChildren.test_add_child_withdraw_and_restore smoke:P1 smoke:P2 smoke:P3 smoke:P4 | N25: Not run
A26: TC-ADM-01 | B26: Admin | D26: Users list and search | E26: P2 | G26: Local | I26: in `/admin/` → Users, search for `Kabir`, `rahul@test.tutor` and `9000000022`; filter by account type *Parent*. | J26: search by name, email or mobile finds the test accounts; filter by account type works. | K26: 0 | N26: Not run
A27: TC-ADM-02 | B27: Admin | D27: Create a user in admin | E27: P2 | G27: Local | I27: add a user with only a mobile. | J27: saved. Adding a user with neither email nor mobile is refused. | K27: 0 | N27: Not run
A28: TC-ADM-03 | B28: Admin | D28: Grant an entitlement | E28: P1 | G28: Local | I28: follow the tester guide §4. | J28: the student can open paid lessons immediately. | K28: 0 | N28: Not run
A29: TC-ADM-04 | B29: Admin | D29: Publish content | E29: P1 | F29: FR-CON-3 | G29: Local | I29: create a new content version for *What is data?* with status `approved`, a reviewer different from the author, edited body. Use the list action Publish selected approved versions. | J29: the new version becomes `published`; the old one becomes `archived`; `GET /lessons/<id>` shows the new text; audit log `content.published`. | K29: 2 | L29: apps.content.tests.AdminPublishingTests.test_lead_publishes_and_it_is_audited apps.catalogue.tests.ContentVersionTests.test_publishing_archives_previous | N29: Not run
A30: TC-ADM-05 | B30: Admin | D30: Publishing a draft is refused | E30: P2 | G30: Local | I30: select a `draft` version and run the publish action. | J30: warning message; nothing changes. | K30: 1 | L30: apps.catalogue.tests.ContentVersionTests.test_only_approved_can_be_published | N30: Not run
A31: TC-ADM-06 | B31: Admin | D31: Publish a question version | E31: P2 | G31: Local | I31: same as TC-ADM-04 under Assessment → Question versions. | J31: new quizzes use the new wording; attempts already started keep the old version. | K31: 1 | L31: apps.content.tests.AdminPublishingTests.test_question_publish_action | N31: Not run
A32: TC-ADM-07 | B32: Admin | D32: Roles | E32: P2 | F32: FR-ACC-9 | G32: Local | I32: as the superuser add a role grant (reviewer, AI Foundations) to a user; add the same active grant again. | J32: first save sets *Granted by* to you and writes audit `role.granted`; second save refused. There is no delete: revoke by setting *Revoked at* (audit `role.revoked`). | K32: 2 | L32: apps.content.tests.RoleAdminTests.test_granting_a_role_is_recorded apps.accounts.tests.RoleTests.test_no_duplicate_active_grant | N32: Not run
A33: TC-ADM-09 | B33: Admin | D33: Curriculum lead publishes only their own subject | E33: P1 | F33: FR-CON-3 | G33: Local | I33: log in to `/admin/` as Lalit (`lalit@test.tutor`). Publish an approved AI Foundations content version. Then, as the superuser, create a Class 8 maths course with a lesson and an approved version; as Lalit try to publish it. | J33: the first publishes (audit `content.published`, actor Lalit); the second is refused with a warning. | K33: 2 | L33: apps.content.tests.PublishPermissionTests.test_lead_for_subject_and_class apps.content.tests.AdminPublishingTests.test_staff_without_role_is_refused | N33: Not run
A34: TC-ADM-10 | B34: Admin | D34: Status can't be set to published by hand | E34: P1 | G34: Local | I34: open an approved content version, change *Status* to `published` and save. Also open a published one and change it to `draft`. | J34: both refused with "Published and archived are set only by the … action". | K34: 2 | L34: apps.content.tests.AdminPublishingTests.test_status_cannot_be_typed_in_as_published apps.content.tests.AdminPublishingTests.test_published_status_cannot_be_changed_back_in_the_form | N34: Not run
A35: TC-ADM-08 | B35: Admin | D35: Mastery and progress are visible | E35: P3 | G35: Local | I35: in `/admin/` open Learning → Mastery states, Mastery events, Lesson progress and Course completions; try to edit a mastery event. | J35: Learning → Mastery states, Mastery events, Lesson progress, Course completions show the smoke-test student's data; mastery events can't be edited. | K35: 0 | N35: Not run
A36: TC-CAT-01 | B36: Catalogue | D36: Facets | E36: P2 | F36: FR-CAT-2 | G36: Local | I36: `GET /catalogue/facets`. | J36: classes 6–12; boards CBSE, ICSE, WBBSE; 5 path stages; disciplines with subjects. | K36: 1 | L36: apps.catalogue.tests.CatalogueApiTests.test_facets | N36: Not run
A37: TC-CAT-02 | B37: Catalogue | D37: Items list shows only published | E37: P1 | F37: FR-CAT-2 | G37: Local | H37: in admin, create a course with status `draft`. | I37: `GET /catalogue/items`. | J37: AI Foundations and "Explore AI (Class 8)" listed; the draft course not listed. | K37: 3 | L37: apps.catalogue.tests.CatalogueApiTests.test_items_lists_published_only smoke:C1 hosted:C1 | N37: Not run
A38: TC-CAT-03 | B38: Catalogue | D38: Filters | E38: P2 | F38: FR-CAT-2 | G38: Local | I38: `?type=course`, `?class_number=8`, `?board=icse`, `?subject=ai-foundations`, `?stage=2`. | J38: board-independent courses (AI Foundations) appear for any class or board; `type=course` excludes programmes. | K38: 2 | L38: apps.catalogue.tests.CatalogueApiTests.test_board_filter_keeps_board_independent_courses apps.catalogue.tests.CatalogueApiTests.test_class_filter | N38: Not run
A39: TC-CAT-04 | B39: Catalogue | D39: Pagination | E39: P3 | G39: Local | I39: `?page_size=1&page=2`. | J39: one result; `page: 2`; `total` equals the unpaginated count. `page_size=500` is capped at 50. | K39: 2 | L39: apps.catalogue.tests.CatalogueApiTests.test_pagination apps.catalogue.test_queries.CatalogueQueryTests.test_items_are_paginated_in_the_database | N39: Not run
A40: TC-CAT-05 | B40: Catalogue | D40: Course page | E40: P1 | G40: Local | I40: `GET /courses/ai-foundations`. | J40: 3 lessons, all `is_free: true` and `has_content: true`; 4 skills; `path_stage_label: "Explore"`; `price_paise: 49900`. | K40: 3 | L40: apps.catalogue.tests.CatalogueApiTests.test_course_detail smoke:C2 hosted:C2 | N40: Not run
A41: TC-CAT-06 | B41: Catalogue | D41: Unknown or draft course | E41: P2 | G41: Local | I41: `GET /courses/does-not-exist`, then `GET /courses/biology-class-12` (a draft course). | J41: `404 not_found` for a wrong slug and for a draft course's slug. | K41: 2 | L41: apps.catalogue.tests.CatalogueApiTests.test_draft_course_is_404 hosted:C5 | N41: Not run
A42: TC-CAT-07 | B42: Catalogue | D42: Programme page | E42: P2 | G42: Local | I42: `GET /programmes/explore-ai-class-8`. | J42: class 8; courses list contains AI Foundations with its price. | K42: 1 | L42: apps.catalogue.tests.CatalogueApiTests.test_programme_detail | N42: Not run
A43: TC-CAT-08 | B43: Catalogue | D43: Free preview | E43: P1 | F43: FR-CAT-3 | G43: Local | I43: `GET /lessons/<first lesson id>/preview`. | J43: `200` with sections; no quiz, no tutor. | K43: 2 | L43: apps.catalogue.tests.CatalogueApiTests.test_free_lesson_preview hosted:C4 | N43: Not run
A44: TC-CAT-09 | B44: Catalogue | D44: Preview of a paid lesson refused | E44: P1 | F44: FR-CAT-3 | G44: Local | H44: in admin add a second module (not free) to AI Foundations with one lesson. | I44: preview that lesson. | J44: `403 not_entitled`. | K44: 1 | L44: apps.catalogue.tests.CatalogueApiTests.test_paid_lesson_preview_is_blocked | N44: Not run
A45: TC-HOST-01 | B45: Demo world & hosted | C45: Hosted demo | D45: Hosted smoke checks | E45: P1 | F45: NFR-AVAIL-1 | G45: Hosted | I45: from `backend/`, `python qa/smoke_test.py --hosted --base https://tutor-platform-ovlg.onrender.com`. | J45: every line `PASS`; last line `17/17 checks passed` (the count grows as checks are added). | K45: 3 | L45: hosted:H1 hosted:C1 hosted:X1 | N45: Not run
A46: TC-HOST-02 | B46: Demo world & hosted | C46: Hosted demo | D46: Root page and docs | E46: P3 | G46: Hosted | I46: open the site root `/`, then `/api/v1/docs`. | J46: JSON pointing to `/api/v1/docs`, `/api/v1/health` and `/admin/`; the docs page lists every endpoint. | K46: 2 | L46: apps.core.tests.RootPageTests.test_root_points_to_the_api hosted:H5 | N46: Not run
A47: TC-HOST-03 | B47: Demo world & hosted | C47: Hosted demo | D47: Tester tools are off | E47: P1 | F47: NFR-SEC-1 | G47: Hosted | I47: `GET /dev/outbox` on the hosted site. | J47: `404`. | K47: 1 | L47: hosted:X3 | N47: Not run
A48: TC-HOST-04 | B48: Demo world & hosted | C48: Hosted demo | D48: HTTPS enforced | E48: P1 | F48: NFR-SEC-2 | G48: Hosted | I48: open `http://tutor-platform-ovlg.onrender.com/api/v1/catalogue/facets` (plain http). | J48: redirected to `https://`; responses carry `Strict-Transport-Security`. | K48: 2 | L48: hosted:H2 hosted:H4 | N48: Not run
A49: TC-DEMO-01 | B49: Demo world & hosted | C49: Demo people | D49: Every demo account logs in | E49: P1 | F49: FR-ACC-1 | G49: Local or hosted | I49: `POST /auth/login` with each account in demo-data.md (email or 10-digit mobile). | J49: `200`; `GET /me` shows the right name, account type and roles. | K49: 1 | L49: apps.demo.tests.DemoWorldTests.test_everyone_logs_in_with_the_demo_password | N49: Not run
A50: TC-DEMO-02 | B50: Demo world & hosted | C50: Demo people | D50: Consent states are enforced | E50: P1 | F50: FR-LRN-1 | G50: Local or hosted | I50: as Wasim (waiting) and Rohan (paused), open any lesson. | J50: `403 consent_required` for both. As Farhan, restore Rohan's consent (`POST /parent/children/<rohan id>/consent/restore`); Rohan can open lessons again and his old quiz is still in `GET /student/record`. | K50: 2 | L50: apps.demo.tests.DemoWorldTests.test_student_states apps.demo.tests.DemoWorldTests.test_paused_student_keeps_history_but_is_blocked | N50: Not run
A51: TC-DEMO-03 | B51: Demo world & hosted | C51: Demo people | D51: Entitlements differ per student | E51: P1 | F51: FR-LRN-2 | G51: Local or hosted | I51: open a Module 2 lesson of Mathematics · Class 8 as Asha, Kabir and Rohan-after-restore. | J51: Asha `403 not_entitled`; Kabir `200` (programme); Rohan `200` (course). | K51: 0 | N51: Not run
A52: TC-DEMO-04 | B52: Demo world & hosted | C52: Demo people | D52: Kabir's record | E52: P1 | F52: FR-LRN-5, FR-LRN-6 | G52: Local or hosted | I52: as Kabir, `GET /student/record` and `GET /student/today`. | J52: AI Foundations under completed courses; 7 quizzes; skill `M8-RAT-02` weak; Today's `review` points at a Rational numbers lesson. | K52: 2 | L52: apps.demo.tests.DemoWorldTests.test_kabir_sees_his_record_and_a_review_item apps.demo.tests.DemoWorldTests.test_learning_history | N52: Not run
A53: TC-DEMO-05 | B53: Demo world & hosted | C53: Demo people | D53: Streaks | E53: P3 | F53: NFR-TIME-1 | G53: Local or hosted | I53: right after `seed_demo --reset-activity`, `GET /student/today` as Zoya and Meera. | J53: `streak_days` 5 and 3. On later days the numbers drop (streaks are real), which is correct. | K53: 2 | L53: apps.demo.tests.DemoWorldTests.test_learning_history apps.demo.tests.DemoWorldTests.test_reset_activity_rebuilds_history | N53: Not run
A54: TC-DEMO-06 | B54: Demo world & hosted | C54: Demo people | D54: Draft course never shown | E54: P1 | F54: FR-CAT-2 | G54: Local or hosted | I54: `GET /catalogue/items?page_size=50`, then `GET /courses/biology-class-12`. | J54: not listed; `404`. | K54: 1 | L54: apps.demo.tests.DemoWorldTests.test_draft_course_is_hidden_from_the_public_catalogue | N54: Not run
A55: TC-DEMO-07 | B55: Demo world & hosted | C55: Product admins (roles, not Django superusers) | D55: Maya publishes the approved Maths version | E55: P1 | F55: FR-CON-3 | G55: Local or hosted | I55: log in to `/admin/` as Maya; Content versions → filter *approved* → *Solving linear equations* → action Publish selected approved versions. | J55: published, old version archived, audit entry with Maya as actor; `GET /lessons/<id>` as Kabir shows the "What's new in this version" section. | K55: 1 | L55: apps.demo.tests.DemoWorldTests.test_content_waiting_in_every_review_state | N55: Not run
A56: TC-DEMO-08 | B56: Demo world & hosted | C56: Product admins (roles, not Django superusers) | D56: Leads are limited to their subject | E56: P1 | F56: NFR-SEC-5 | G56: Local or hosted | I56: as Lalit, try to publish a Maths version; as Maya, try to publish Tara's AI Foundations draft after an admin approves it. | J56: both refused with "Only the curriculum lead…"; nothing changes. | K56: 1 | L56: apps.demo.tests.DemoWorldTests.test_publishing_rights_match_the_roles | N56: Not run
A57: TC-DEMO-09 | B57: Demo world & hosted | C57: Product admins (roles, not Django superusers) | D57: Operations cannot publish, can enrol | E57: P1 | F57: NFR-SEC-5 | G57: Local or hosted | I57: as Omar, open Content versions (not visible or read-only), then Entitlements → add one for Ishaan on Physics · Class 11. | J57: cannot publish; the entitlement saves and Ishaan can open Physics Module 2 lessons. | K57: 1 | L57: apps.demo.tests.DemoWorldTests.test_publishing_rights_match_the_roles | N57: Not run
A58: TC-DEMO-10 | B58: Demo world & hosted | C58: Product admins (roles, not Django superusers) | D58: Only the super admin grants roles | E58: P1 | F58: NFR-SEC-5 | G58: Local or hosted | I58: as Ananya, add a *reviewer* role for Tara on Mathematics. As Maya, try the same. | J58: Ananya's grant saves with *Granted by* = Ananya and an audit entry; Maya sees no Add button. | K58: 2 | L58: apps.demo.tests.DemoWorldTests.test_four_product_admins apps.content.tests.RoleAdminTests.test_only_super_admins_grant_roles | N58: Not run
A59: TC-DEMO-11 | B59: Demo world & hosted | C59: Product admins (roles, not Django superusers) | D59: Review states are visible | E59: P2 | F59: FR-CON-2 | G59: Local or hosted | I59: as Ananya in Content versions, filter by status. | J59: one draft (Tara, What is data?), one in review (Vikram → Neha), one approved (Solving linear equations) until TC-DEMO-07 publishes it. | K59: 1 | L59: apps.demo.tests.DemoWorldTests.test_content_waiting_in_every_review_state | N59: Not run
A60: TC-LRN-01 | B60: Learning & quizzes | D60: Open a lesson | E60: P1 | F60: FR-LRN-1 | G60: Local | H60: logged in as Esha. | I60: `GET /lessons/<id>`. | J60: `200`, sections, skills, `has_quiz: true`. Admin → Lesson progress shows `opened`. | K60: 2 | L60: apps.learning.tests.AccessTests.test_free_lesson_open_without_purchase smoke:L1 | N60: Not run
A61: TC-LRN-02 | B61: Learning & quizzes | D61: Waiting student blocked | E61: P1 | F61: FR-LRN-1 | G61: Local | H61: logged in as Wasim. | I61: open a lesson; start a quiz; `GET /student/today`. | J61: `403 consent_required` for all three. | K61: 2 | L61: apps.learning.tests.AccessTests.test_consent_required smoke:A2 | N61: Not run
A62: TC-LRN-03 | B62: Learning & quizzes | D62: Entitlement gate | E62: P1 | F62: FR-LRN-2 | G62: Local | H62: TC-CAT-09's paid lesson exists. | I62: Asha (no purchase) opens it; Esha (entitled) opens it. | J62: Asha `403 not_entitled`; Esha `200` if the lesson has published content, otherwise `404` (allowed, but empty). | K62: 2 | L62: apps.learning.tests.AccessTests.test_paid_lesson_needs_entitlement apps.learning.tests.AccessTests.test_programme_entitlement_covers_its_courses | N62: Not run
A63: TC-LRN-04 | B63: Learning & quizzes | D63: Entitlement revoked or expired | E63: P1 | F63: FR-LRN-2 | G63: Local | I63: in admin set Esha's entitlement `revoked_at` (or `ends_at` in the past); open the paid lesson. | J63: `403 not_entitled`. Clear the field and it works again. | K63: 1 | L63: apps.learning.tests.AccessTests.test_revoked_entitlement | N63: Not run
A64: TC-LRN-05 | B64: Learning & quizzes | D64: Finish a lesson | E64: P2 | G64: Local | I64: `POST /lessons/<id>/finish`. | J64: `finished: true`, `next_lesson_id` points to the next unfinished lesson. | K64: 0 | N64: Not run
A65: TC-QZ-01 | B65: Learning & quizzes | D65: Start a quiz; no answers leaked | E65: P1 | F65: FR-LRN-3 | G65: Local | I65: `POST /lessons/<id>/quiz/start`. | J65: `attempt_id`; each item has stem, options, `hints_available`; the response contains no `answer_index`, explanation or misconception. | K65: 2 | L65: apps.learning.tests.QuizFlowTests.test_quiz_does_not_leak_answers smoke:Q1 | N65: Not run
A66: TC-QZ-02 | B66: Learning & quizzes | D66: Resume, don't duplicate | E66: P2 | G66: Local | I66: start the same quiz twice without submitting. | J66: the same `attempt_id` both times. | K66: 1 | L66: apps.learning.test_queries.LearningQueryTests.test_resume_quiz | N66: Not run
A67: TC-QZ-03 | B67: Learning & quizzes | D67: Hints | E67: P1 | F67: FR-LRN-4 | G67: Local | I67: `POST /attempts/<id>/hint {"position": 1}` until refused. | J67: each returns the next hint and `hints_left`; after the last, `409`. Hints after answering that question: `409`. | K67: 2 | L67: apps.learning.tests.QuizFlowTests.test_full_quiz smoke:Q2 | N67: Not run
A68: TC-QZ-04 | B68: Learning & quizzes | D68: Correct answer | E68: P1 | G68: Local | I68: answer position 1 correctly. | J68: `correct: true`, `correct_index`, explanation, mastery for the skill with `score > 0`. | K68: 1 | L68: apps.learning.tests.QuizFlowTests.test_full_quiz | N68: Not run
A69: TC-QZ-05 | B69: Learning & quizzes | D69: Wrong answer with misconception | E69: P1 | G69: Local | I69: on *What is data?* answer position 2 with option 1. | J69: `correct: false`, misconception "Who won is the label here." | K69: 1 | L69: apps.learning.tests.QuizFlowTests.test_full_quiz | N69: Not run
A70: TC-QZ-06 | B70: Learning & quizzes | D70: Can't answer twice; bad option | E70: P1 | G70: Local | I70: in an open attempt, answer position 1, then answer position 1 again; then answer position 2 with `choice_index: 9`. | J70: second answer `409`; `choice_index: 9` → `400 validation_error`. | K70: 2 | L70: apps.learning.tests.QuizFlowTests.test_full_quiz smoke:Q4 | N70: Not run
A71: TC-QZ-07 | B71: Learning & quizzes | D71: Submit | E71: P1 | G71: Local | I71: answer every question, `POST /attempts/<id>/submit`, then submit again. | J71: `score` / `max_score`; `skill_changes` with `before` and `after` per skill; submitting again `409`; the lesson is now finished. | K71: 2 | L71: apps.learning.tests.QuizFlowTests.test_full_quiz smoke:Q5 | N71: Not run
A72: TC-QZ-08 | B72: Learning & quizzes | D72: Someone else's attempt | E72: P1 | G72: Local | I72: Asha starts a quiz; Esha tries to answer or submit Asha's `attempt_id`. | J72: `404` (not `403`, which would reveal that the attempt exists). | K72: 1 | L72: apps.learning.tests.QuizFlowTests.test_other_students_attempt_is_invisible | N72: Not run
A73: TC-MAS-01 | B73: Learning & quizzes | D73: Mastery rule | E73: P1 | F73: FR-LRN-4, FR-LRN-5 | G73: Local | I73: with a fresh student, answer three questions on skill `AI-DATA-01` correctly with no hints. | J73: scores ≈ 0.35 → 0.5775 → 0.7254; level `developing` (not `mastered`: needs ≥ 0.75). Admin → Mastery events shows three rows, each linked to its answer. | K73: 1 | L73: apps.learning.tests.MasteryRuleTests.test_levels | N73: Not run
A74: TC-MAS-02 | B74: Learning & quizzes | D74: Hint penalty | E74: P2 | F74: FR-LRN-4 | G74: Local | I74: fresh student; one hint on a question, then answer correctly. | J74: score 0.2625 (credit 0.75 × 0.35), not 0.35. | K74: 1 | L74: apps.learning.tests.MasteryRuleTests.test_hint_penalty | N74: Not run
A75: TC-MAS-03 | B75: Learning & quizzes | D75: Course completion | E75: P1 | F75: FR-LRN-6 | G75: Local | H75: Esha, with no extra paid lesson in the course. | I75: take all three quizzes with the correct answers. | J75: last submit returns `course_completed: true`; `GET /student/record` lists AI Foundations in `completed_courses`; `GET /student/today` has `next_lesson: null`. | K75: 1 | L75: apps.learning.tests.QuizFlowTests.test_course_completion_and_today | N75: Not run
A76: TC-TDY-01 | B76: Learning & quizzes | D76: Today | E76: P1 | F76: FR-LRN-7 | G76: Local | I76: after a few answers (some wrong), `GET /student/today`. | J76: `next_lesson` = first unfinished accessible lesson; `review` names the weakest practised skill; `streak_days ≥ 1`. | K76: 2 | L76: apps.learning.tests.QuizFlowTests.test_course_completion_and_today smoke:R2 | N76: Not run
A77: TC-TDY-02 | B77: Learning & quizzes | D77: Streak uses India time | E77: P3 | F77: NFR-TIME-1 | G77: Local | I77: answer a question between 00:00 and 05:30 IST; check Today. | J77: `streak_days ≥ 1` (not 0). | K77: 2 | L77: apps.learning.test_queries.StreakTests.test_streak_stops_at_the_first_gap apps.demo.tests.StudyTimeTests.test_study_time_is_10am_ist_and_never_in_the_future | N77: Not run
A78: TC-REC-01 | B78: Learning & quizzes | D78: My record | E78: P1 | G78: Local | I78: as Kabir (or a student who has taken a quiz), `GET /student/record`. | J78: mastery per skill (code, name, level, score, evidence); completed courses; quiz history newest first; `lessons_finished`. | K78: 2 | L78: apps.learning.tests.QuizFlowTests.test_full_quiz smoke:R1 | N78: Not run
A79: TC-SEC-01 | B79: Security & privacy | D79: Anonymous access | E79: P1 | F79: NFR-SEC-1 | G79: Local | I79: logged out, call `GET /me`, `GET /student/today`, `GET /student/record`, `GET /lessons/<id>`, `POST /parent/children`. | J79: `401 not_authenticated` for each. | K79: 3 | L79: apps.accounts.test_api.SecureByDefaultTests.test_protected_endpoints_need_login hosted:X1 hosted:X2 | N79: Not run
A80: TC-SEC-02 | B80: Security & privacy | D80: Parent can only act on their own children | E80: P1 | G80: Local | I80: a different verified parent withdraws consent for Asha's ID. | J80: `404 not_found`; Asha unaffected. | K80: 1 | L80: apps.accounts.test_api.ParentManagesChildren.test_other_parent_cannot_touch_child | N80: Not run
A81: TC-SEC-03 | B81: Security & privacy | D81: Student can't approve their own account | E81: P1 | G81: Local | I81: the waiting student signs up as a parent with a second contact and tries to approve their own link while logged in as the student account. | J81: `403`. | K81: 0 | N81: Not run
A82: TC-SEC-04 | B82: Security & privacy | D82: Consent gates every learning action | E82: P1 | G82: Local | I82: as Wasim (waiting), try lesson, finish, quiz start, hint, answer, submit, today, record. | J82: `403 consent_required` for each. | K82: 2 | L82: apps.learning.tests.AccessTests.test_consent_required smoke:P2 | N82: Not run
A83: TC-SEC-05 | B83: Security & privacy | D83: Secrets are stored hashed | E83: P1 | F83: NFR-SEC-3 | G83: Local | I83: Admin → Approval requests and Verification codes. | J83: only 64-character hashes; the raw link token or code from the outbox appears nowhere in admin. | K83: 1 | L83: apps.accounts.tests.TokenAndApprovalTests.test_link_token_stored_only_as_hash | N83: Not run
A84: TC-SEC-06 | B84: Security & privacy | D84: Consent evidence | E84: P1 | F84: FR-ACC-5 | G84: Local | I84: after an approval, open the consent record in admin. | J84: consent text version, time, IP. Admin → Consent texts: an existing text can't be edited. | K84: 1 | L84: apps.accounts.tests.GuardianConsentTests.test_consent_record_active_until_withdrawn | N84: Not run
A85: TC-SEC-07 | B85: Security & privacy | D85: Audit log is read-only | E85: P1 | F85: FR-OPS-1 | G85: Local | I85: Admin → Audit log. | J85: entries for consent given/withdrawn/restored and content publishing; no add, edit or delete buttons. | K85: 1 | L85: apps.core.tests.AuditLogAdminTests.test_audit_log_is_read_only_even_for_superusers | N85: Not run
A86: TC-SEC-08 | B86: Security & privacy | D86: Published content can't be edited | E86: P1 | F86: FR-CON-1 | G86: Local | I86: Admin → Content versions → a published version. | J86: body, lesson and version number are read-only. Creating a second published version for the same lesson directly fails. | K86: 2 | L86: apps.catalogue.tests.ContentVersionTests.test_one_published_version_per_lesson apps.content.tests.AdminPublishingTests.test_published_status_cannot_be_changed_back_in_the_form | N86: Not run
A87: TC-SEC-09 | B87: Security & privacy | D87: Reviewer ≠ author | E87: P2 | F87: FR-CON-2 | G87: Local | I87: in admin, set a content version's reviewer to its author. | J87: save refused (database constraint). | K87: 1 | L87: apps.catalogue.tests.ContentVersionTests.test_reviewer_cannot_be_author | N87: Not run
A88: TC-SEC-10 | B88: Security & privacy | D88: Enumeration resistance | E88: P2 | F88: FR-ACC-3 | G88: Local | I88: `POST /auth/otp/send` for a registered and an unregistered number. | J88: identical responses. | K88: 1 | L88: apps.accounts.test_api.LoginAndErrors.test_otp_not_sent_to_unknown_contact | N88: Not run
A89: TC-SEC-11 | B89: Security & privacy | D89: Dev tools not in production mode | E89: P1 | G89: Local | I89: set `DJANGO_DEBUG=false` in `.env`, restart, `GET /dev/outbox`; run `python manage.py seed_test_accounts`. | J89: `404`; command refuses. Restore `DJANGO_DEBUG=true` afterwards. (Also covered by automated tests.) | K89: 3 | L89: apps.accounts.tests.DevToolsAreLockedTests.test_seed_test_accounts_refuses_without_dev_flags apps.accounts.tests.DevToolsAreLockedTests.test_dev_outbox_not_mounted_when_debug_off hosted:X3 | N89: Not run
A90: TC-SEC-12 | B90: Security & privacy | D90: No data minimisation regressions | E90: P2 | F90: NFR-PRIV-1 | G90: Local | I90: review `GET /me`, `GET /consent/link/<token>`. | J90: no date of birth anywhere; the approval page shows only the child's first name and class. | K90: 0 | N90: Not run
A91: TC-SEC-13 | B91: Security & privacy | D91: Login lockout | E91: P1 | F91: NFR-SEC-4 | G91: Local | I91: `POST /auth/login` for Wasim (`9000000004`) with a wrong password 10 times, then once with `Test-Pass-2026`. | J91: first 9 → `400 invalid_credentials`; 10th and the correct password → `429 login_locked`. Other accounts still log in. To unlock (running `seed_test_accounts` does not): wait 15 minutes, or reset Wasim's password with a one-time code (`/auth/otp/send` purpose `reset_password` → `/auth/password/reset`), which lifts the lock at once. | K91: 2 | L91: apps.accounts.test_security.LoginLockoutTests.test_account_locks_after_repeated_wrong_passwords apps.accounts.test_security.LoginLockoutTests.test_password_reset_lifts_the_lockout | N91: Not run
A92: TC-SEC-14 | B92: Security & privacy | D92: Lockout doesn't reveal accounts | E92: P2 | F92: FR-ACC-3 | G92: Local | I92: repeat TC-SEC-13 with `nobody@test.tutor` (no such account). | J92: identical responses, including the 10th. | K92: 1 | L92: apps.accounts.test_security.LoginLockoutTests.test_unknown_accounts_lock_the_same_way | N92: Not run
A93: TC-SEC-15 | B93: Security & privacy | D93: Rate limit on login | E93: P2 | F93: NFR-SEC-4 | G93: Local | I93: send more than 30 `POST /auth/login` requests within one minute (any credentials; a small script or repeated "Execute" in `/docs`). | J93: from the 31st, `429 limit_reached` with a `Retry-After` header; after a minute it works again. | K93: 1 | L93: apps.accounts.test_security.RateLimitTests.test_login_is_rate_limited_per_ip | N93: Not run
A94: TC-SEC-16 | B94: Security & privacy | D94: Forged X-Forwarded-For doesn't bypass limits | E94: P2 | F94: NFR-SEC-4 | G94: Local | I94: repeat TC-SEC-15 adding a different `X-Forwarded-For` header on every request (e.g. with curl `-H`). | J94: still limited after 30 (locally the header is ignored entirely; see D21). | K94: 2 | L94: apps.accounts.test_security.RateLimitTests.test_forging_x_forwarded_for_does_not_escape_the_limit apps.accounts.test_security.ClientIpTests.test_forged_left_entries_are_ignored | N94: Not run
A95: TC-SEC-17 | B95: Security & privacy | D95: Only curriculum leads publish | E95: P1 | F95: FR-CON-3 | G95: Local | I95: log in to `/admin/` as a staff user who has content permissions but no curriculum-lead role (create one as the superuser, or temporarily revoke Lalit's role), select an approved AI Foundations version, run Publish selected approved versions. | J95: warning "Only the curriculum lead…"; nothing published. With Lalit (lead) it publishes. | K95: 2 | L95: apps.content.tests.AdminPublishingTests.test_staff_without_role_is_refused apps.content.tests.PublishPermissionTests.test_reviewer_without_lead_role_cannot_publish | N95: Not run
A96: TC-SEC-18 | B96: Security & privacy | D96: Staff can't promote themselves | E96: P1 | F96: NFR-SEC-5 | G96: Local | I96: as Lalit in `/admin/`, open his own user record (give him `change_user` first if needed). | J96: Staff status, Superuser status, Groups and Permissions are read-only. Role grants: no Add button, no delete. | K96: 2 | L96: apps.content.tests.RoleAdminTests.test_staff_cannot_give_themselves_admin_access apps.content.tests.RoleAdminTests.test_only_super_admins_grant_roles | N96: Not run

Sheet Automated tests
A1: Test label | B1: App | C1: Layer | D1: Class | E1: What it proves | F1: Covers manual cases | G1: Run it (from backend/)
A2: apps.accounts.test_api.SignupAndApprovalFlow.test_student_signup_waits_for_parent | B2: accounts | C2: API | D2: SignupAndApprovalFlow | E2: Student signup waits for parent | F2: TC-ACC-01 | G2: python manage.py test apps.accounts.test_api.SignupAndApprovalFlow.test_student_signup_waits_for_parent --settings=config.settings.test
A3: apps.accounts.test_api.SignupAndApprovalFlow.test_full_approval | B3: accounts | C3: API | D3: SignupAndApprovalFlow | E3: Full approval | F3: TC-ACC-02, TC-CON-02 | G3: python manage.py test apps.accounts.test_api.SignupAndApprovalFlow.test_full_approval --settings=config.settings.test
A4: apps.accounts.test_api.SignupAndApprovalFlow.test_parent_must_verify_contact_first | B4: accounts | C4: API | D4: SignupAndApprovalFlow | E4: Parent must verify contact first | F4: TC-CON-03 | G4: python manage.py test apps.accounts.test_api.SignupAndApprovalFlow.test_parent_must_verify_contact_first --settings=config.settings.test
A5: apps.accounts.test_api.SignupAndApprovalFlow.test_not_my_child | B5: accounts | C5: API | D5: SignupAndApprovalFlow | E5: Not my child | F5: TC-CON-06 | G5: python manage.py test apps.accounts.test_api.SignupAndApprovalFlow.test_not_my_child --settings=config.settings.test
A6: apps.accounts.test_api.SignupAndApprovalFlow.test_resend_limit | B6: accounts | C6: API | D6: SignupAndApprovalFlow | E6: Resend limit | F6: TC-CON-07 | G6: python manage.py test apps.accounts.test_api.SignupAndApprovalFlow.test_resend_limit --settings=config.settings.test
A7: apps.accounts.test_api.SignupAndApprovalFlow.test_change_parent_contact | B7: accounts | C7: API | D7: SignupAndApprovalFlow | E7: Change parent contact | F7: TC-CON-08 | G7: python manage.py test apps.accounts.test_api.SignupAndApprovalFlow.test_change_parent_contact --settings=config.settings.test
A8: apps.accounts.test_api.LoginAndErrors.test_login_with_plain_10_digit_mobile | B8: accounts | C8: API | D8: LoginAndErrors | E8: Login with plain 10 digit mobile | F8: TC-ACC-05 | G8: python manage.py test apps.accounts.test_api.LoginAndErrors.test_login_with_plain_10_digit_mobile --settings=config.settings.test
A9: apps.accounts.test_api.LoginAndErrors.test_wrong_password | B9: accounts | C9: API | D9: LoginAndErrors | E9: Wrong password | F9: TC-ACC-06 | G9: python manage.py test apps.accounts.test_api.LoginAndErrors.test_wrong_password --settings=config.settings.test
A10: apps.accounts.test_api.LoginAndErrors.test_duplicate_signup | B10: accounts | C10: API | D10: LoginAndErrors | E10: Duplicate signup | F10: TC-ACC-03 | G10: python manage.py test apps.accounts.test_api.LoginAndErrors.test_duplicate_signup --settings=config.settings.test
A11: apps.accounts.test_api.LoginAndErrors.test_validation_error_format | B11: accounts | C11: API | D11: LoginAndErrors | E11: Validation error format | F11: TC-ACC-04 | G11: python manage.py test apps.accounts.test_api.LoginAndErrors.test_validation_error_format --settings=config.settings.test
A12: apps.accounts.test_api.LoginAndErrors.test_me_requires_login | B12: accounts | C12: API | D12: LoginAndErrors | E12: Me requires login | G12: python manage.py test apps.accounts.test_api.LoginAndErrors.test_me_requires_login --settings=config.settings.test
A13: apps.accounts.test_api.LoginAndErrors.test_otp_not_sent_to_unknown_contact | B13: accounts | C13: API | D13: LoginAndErrors | E13: Otp not sent to unknown contact | F13: TC-ACC-10, TC-SEC-10 | G13: python manage.py test apps.accounts.test_api.LoginAndErrors.test_otp_not_sent_to_unknown_contact --settings=config.settings.test
A14: apps.accounts.test_api.LoginAndErrors.test_password_reset | B14: accounts | C14: API | D14: LoginAndErrors | E14: Password reset | F14: TC-ACC-08 | G14: python manage.py test apps.accounts.test_api.LoginAndErrors.test_password_reset --settings=config.settings.test
A15: apps.accounts.test_api.ParentManagesChildren.test_add_child_withdraw_and_restore | B15: accounts | C15: API | D15: ParentManagesChildren | E15: Add child withdraw and restore | F15: TC-CON-10, TC-CON-11 | G15: python manage.py test apps.accounts.test_api.ParentManagesChildren.test_add_child_withdraw_and_restore --settings=config.settings.test
A16: apps.accounts.test_api.ParentManagesChildren.test_other_parent_cannot_touch_child | B16: accounts | C16: API | D16: ParentManagesChildren | E16: Other parent cannot touch child | F16: TC-SEC-02 | G16: python manage.py test apps.accounts.test_api.ParentManagesChildren.test_other_parent_cannot_touch_child --settings=config.settings.test
A17: apps.accounts.test_api.SecureByDefaultTests.test_docs_page_sends_csrf_token | B17: accounts | C17: API | D17: SecureByDefaultTests | E17: TC-SET-3: the /docs page must send X-CSRFToken so logged-in POSTs work from Swagger. | F17: TC-SET-3 | G17: python manage.py test apps.accounts.test_api.SecureByDefaultTests.test_docs_page_sends_csrf_token --settings=config.settings.test
A18: apps.accounts.test_api.SecureByDefaultTests.test_public_endpoints_stay_public | B18: accounts | C18: API | D18: SecureByDefaultTests | E18: Public endpoints stay public | G18: python manage.py test apps.accounts.test_api.SecureByDefaultTests.test_public_endpoints_stay_public --settings=config.settings.test
A19: apps.accounts.test_api.SecureByDefaultTests.test_protected_endpoints_need_login | B19: accounts | C19: API | D19: SecureByDefaultTests | E19: Protected endpoints need login | F19: TC-SEC-01 | G19: python manage.py test apps.accounts.test_api.SecureByDefaultTests.test_protected_endpoints_need_login --settings=config.settings.test
A20: apps.accounts.test_dev_tools.SeedTestAccountsTests.test_every_account_can_log_in_by_mobile_and_email | B20: accounts | C20: Integration | D20: SeedTestAccountsTests | E20: Every account can log in by mobile and email | G20: python manage.py test apps.accounts.test_dev_tools.SeedTestAccountsTests.test_every_account_can_log_in_by_mobile_and_email --settings=config.settings.test
A21: apps.accounts.test_dev_tools.SeedTestAccountsTests.test_student_states | B21: accounts | C21: Integration | D21: SeedTestAccountsTests | E21: Student states | G21: python manage.py test apps.accounts.test_dev_tools.SeedTestAccountsTests.test_student_states --settings=config.settings.test
A22: apps.accounts.test_dev_tools.SeedTestAccountsTests.test_parent_is_guardian_of_the_active_students_only | B22: accounts | C22: Integration | D22: SeedTestAccountsTests | E22: Parent is guardian of the active students only | G22: python manage.py test apps.accounts.test_dev_tools.SeedTestAccountsTests.test_parent_is_guardian_of_the_active_students_only --settings=config.settings.test
A23: apps.accounts.test_dev_tools.SeedTestAccountsTests.test_asha_has_nothing_and_esha_has_ai_foundations | B23: accounts | C23: Integration | D23: SeedTestAccountsTests | E23: Asha has nothing and esha has ai foundations | G23: python manage.py test apps.accounts.test_dev_tools.SeedTestAccountsTests.test_asha_has_nothing_and_esha_has_ai_foundations --settings=config.settings.test
A24: apps.accounts.test_dev_tools.SeedTestAccountsTests.test_teacher_can_author_and_review_but_not_publish | B24: accounts | C24: Integration | D24: SeedTestAccountsTests | E24: Teacher can author and review but not publish | G24: python manage.py test apps.accounts.test_dev_tools.SeedTestAccountsTests.test_teacher_can_author_and_review_but_not_publish --settings=config.settings.test
A25: apps.accounts.test_dev_tools.SeedTestAccountsTests.test_lead_can_open_admin_and_publish_ai_foundations | B25: accounts | C25: Integration | D25: SeedTestAccountsTests | E25: Lead can open admin and publish ai foundations | G25: python manage.py test apps.accounts.test_dev_tools.SeedTestAccountsTests.test_lead_can_open_admin_and_publish_ai_foundations --settings=config.settings.test
A26: apps.accounts.test_dev_tools.SeedTestAccountsTests.test_running_again_resets_instead_of_duplicating | B26: accounts | C26: Integration | D26: SeedTestAccountsTests | E26: Running again resets instead of duplicating | G26: python manage.py test apps.accounts.test_dev_tools.SeedTestAccountsTests.test_running_again_resets_instead_of_duplicating --settings=config.settings.test
A27: apps.accounts.test_ensure_superuser.EnsureSuperuserTests.test_skips_when_not_configured | B27: accounts | C27: Integration | D27: EnsureSuperuserTests | E27: Skips when not configured | G27: python manage.py test apps.accounts.test_ensure_superuser.EnsureSuperuserTests.test_skips_when_not_configured --settings=config.settings.test
A28: apps.accounts.test_ensure_superuser.EnsureSuperuserTests.test_creates_superuser_once | B28: accounts | C28: Integration | D28: EnsureSuperuserTests | E28: Creates superuser once | G28: python manage.py test apps.accounts.test_ensure_superuser.EnsureSuperuserTests.test_creates_superuser_once --settings=config.settings.test
A29: apps.accounts.test_ensure_superuser.EnsureSuperuserTests.test_never_resets_an_existing_password | B29: accounts | C29: Integration | D29: EnsureSuperuserTests | E29: Never resets an existing password | G29: python manage.py test apps.accounts.test_ensure_superuser.EnsureSuperuserTests.test_never_resets_an_existing_password --settings=config.settings.test
A30: apps.accounts.test_ensure_superuser.EnsureSuperuserTests.test_never_promotes_an_existing_ordinary_account | B30: accounts | C30: Integration | D30: EnsureSuperuserTests | E30: Never promotes an existing ordinary account | G30: python manage.py test apps.accounts.test_ensure_superuser.EnsureSuperuserTests.test_never_promotes_an_existing_ordinary_account --settings=config.settings.test
A31: apps.accounts.test_ensure_superuser.EnsureSuperuserTests.test_weak_password_is_refused | B31: accounts | C31: Integration | D31: EnsureSuperuserTests | E31: Weak password is refused | G31: python manage.py test apps.accounts.test_ensure_superuser.EnsureSuperuserTests.test_weak_password_is_refused --settings=config.settings.test
... A34: apps.accounts.test_security.ClientIpTests.test_header_ignored_without_trusted_proxies | B34: accounts | C34: Unit | D34: ClientIpTests | E34: Header ignored without trusted proxies | G34: python manage.py test apps.accounts.test_security.ClientIpTests.test_header_ignored_without_trusted_proxies --settings=config.settings.test
A35: apps.accounts.test_security.ClientIpTests.test_forged_left_entries_are_ignored | B35: accounts | C35: Unit | D35: ClientIpTests | E35: Forged left entries are ignored | F35: TC-SEC-16 | G35: python manage.py test apps.accounts.test_security.ClientIpTests.test_forged_left_entries_are_ignored --settings=config.settings.test
A36: apps.accounts.test_security.ClientIpTests.test_two_proxies | B36: accounts | C36: Unit | D36: ClientIpTests | E36: Two proxies | G36: python manage.py test apps.accounts.test_security.ClientIpTests.test_two_proxies --settings=config.settings.test
A37: apps.accounts.test_security.ClientIpTests.test_no_header_falls_back_to_remote_addr | B37: accounts | C37: Unit | D37: ClientIpTests | E37: No header falls back to remote addr | G37: python manage.py test apps.accounts.test_security.ClientIpTests.test_no_header_falls_back_to_remote_addr --settings=config.settings.test
A38: apps.accounts.test_security.RateLimitTests.test_login_is_rate_limited_per_ip | B38: accounts | C38: API | D38: RateLimitTests | E38: Login is rate limited per ip | F38: TC-SEC-15 | G38: python manage.py test apps.accounts.test_security.RateLimitTests.test_login_is_rate_limited_per_ip --settings=config.settings.test
A39: apps.accounts.test_security.RateLimitTests.test_limit_is_per_client_ip | B39: accounts | C39: API | D39: RateLimitTests | E39: Limit is per client ip | G39: python manage.py test apps.accounts.test_security.RateLimitTests.test_limit_is_per_client_ip --settings=config.settings.test
A40: apps.accounts.test_security.RateLimitTests.test_forging_x_forwarded_for_does_not_escape_the_limit | B40: accounts | C40: API | D40: RateLimitTests | E40: Forging x forwarded for does not escape the limit | F40: TC-SEC-16 | G40: python manage.py test apps.accounts.test_security.RateLimitTests.test_forging_x_forwarded_for_does_not_escape_the_limit --settings=config.settings.test
A41: apps.accounts.test_security.RateLimitTests.test_signup_is_rate_limited | B41: accounts | C41: API | D41: RateLimitTests | E41: Signup is rate limited | G41: python manage.py test apps.accounts.test_security.RateLimitTests.test_signup_is_rate_limited --settings=config.settings.test
A42: apps.accounts.test_security.RateLimitTests.test_one_time_code_endpoints_are_rate_limited | B42: accounts | C42: API | D42: RateLimitTests | E42: One time code endpoints are rate limited | F42: TC-ACC-09 | G42: python manage.py test apps.accounts.test_security.RateLimitTests.test_one_time_code_endpoints_are_rate_limited --settings=config.settings.test
A43: apps.accounts.test_security.RateLimitTests.test_consent_link_pages_are_rate_limited | B43: accounts | C43: API | D43: RateLimitTests | E43: Consent link pages are rate limited | G43: python manage.py test apps.accounts.test_security.RateLimitTests.test_consent_link_pages_are_rate_limited --settings=config.settings.test
A44: apps.accounts.test_security.RateLimitTests.test_general_ceiling_applies_to_every_endpoint | B44: accounts | C44: API | D44: RateLimitTests | E44: General ceiling applies to every endpoint | G44: python manage.py test apps.accounts.test_security.RateLimitTests.test_general_ceiling_applies_to_every_endpoint --settings=config.settings.test
A45: apps.accounts.test_security.RateLimitTests.test_no_rate_configured_means_no_limit | B45: accounts | C45: API | D45: RateLimitTests | E45: No rate configured means no limit | G45: python manage.py test apps.accounts.test_security.RateLimitTests.test_no_rate_configured_means_no_limit --settings=config.settings.test
A46: apps.accounts.test_security.LoginLockoutTests.test_account_locks_after_repeated_wrong_passwords | B46: accounts | C46: API | D46: LoginLockoutTests | E46: Account locks after repeated wrong passwords | F46: TC-SEC-13 | G46: python manage.py test apps.accounts.test_security.LoginLockoutTests.test_account_locks_after_repeated_wrong_passwords --settings=config.settings.test
A47: apps.accounts.test_security.LoginLockoutTests.test_successful_login_resets_the_count | B47: accounts | C47: API | D47: LoginLockoutTests | E47: Successful login resets the count | G47: python manage.py test apps.accounts.test_security.LoginLockoutTests.test_successful_login_resets_the_count --settings=config.settings.test
A48: apps.accounts.test_security.LoginLockoutTests.test_unknown_accounts_lock_the_same_way | B48: accounts | C48: API | D48: LoginLockoutTests | E48: The lockout mustn't reveal which emails or mobiles have accounts. | F48: TC-SEC-14 | G48: python manage.py test apps.accounts.test_security.LoginLockoutTests.test_unknown_accounts_lock_the_same_way --settings=config.settings.test
A49: apps.accounts.test_security.LoginLockoutTests.test_lockout_is_per_account | B49: accounts | C49: API | D49: LoginLockoutTests | E49: Lockout is per account | G49: python manage.py test apps.accounts.test_security.LoginLockoutTests.test_lockout_is_per_account --settings=config.settings.test
A50: apps.accounts.test_security.LoginLockoutTests.test_password_reset_lifts_the_lockout | B50: accounts | C50: API | D50: LoginLockoutTests | E50: Password reset lifts the lockout | F50: TC-SEC-13 | G50: python manage.py test apps.accounts.test_security.LoginLockoutTests.test_password_reset_lifts_the_lockout --settings=config.settings.test
A51: apps.accounts.test_security.LoginLockoutTests.test_lockout_also_protects_the_admin_login | B51: accounts | C51: API | D51: LoginLockoutTests | E51: Lockout also protects the admin login | G51: python manage.py test apps.accounts.test_security.LoginLockoutTests.test_lockout_also_protects_the_admin_login --settings=config.settings.test
A52: apps.accounts.test_security.LoginLockoutTests.test_lockout_expires | B52: accounts | C52: API | D52: LoginLockoutTests | E52: Lockout expires | G52: python manage.py test apps.accounts.test_security.LoginLockoutTests.test_lockout_expires --settings=config.settings.test
A53: apps.accounts.tests.UserModelTests.test_create_with_email | B53: accounts | C53: Integration | D53: UserModelTests | E53: Create with email | G53: python manage.py test apps.accounts.tests.UserModelTests.test_create_with_email --settings=config.settings.test
A54: apps.accounts.tests.UserModelTests.test_create_with_mobile_only | B54: accounts | C54: Integration | D54: UserModelTests | E54: Create with mobile only | G54: python manage.py test apps.accounts.tests.UserModelTests.test_create_with_mobile_only --settings=config.settings.test
A55: apps.accounts.tests.UserModelTests.test_needs_email_or_mobile | B55: accounts | C55: Integration | D55: UserModelTests | E55: Needs email or mobile | G55: python manage.py test apps.accounts.tests.UserModelTests.test_needs_email_or_mobile --settings=config.settings.test
A56: apps.accounts.tests.UserModelTests.test_database_enforces_email_or_mobile | B56: accounts | C56: Integration | D56: UserModelTests | E56: Database enforces email or mobile | G56: python manage.py test apps.accounts.tests.UserModelTests.test_database_enforces_email_or_mobile --settings=config.settings.test
A57: apps.accounts.tests.UserModelTests.test_superuser | B57: accounts | C57: Integration | D57: UserModelTests | E57: Superuser | G57: python manage.py test apps.accounts.tests.UserModelTests.test_superuser --settings=config.settings.test
A58: apps.accounts.tests.LoginTests.test_login_with_email | B58: accounts | C58: Integration | D58: LoginTests | E58: Login with email | F58: TC-ACC-05 | G58: python manage.py test apps.accounts.tests.LoginTests.test_login_with_email --settings=config.settings.test
A59: apps.accounts.tests.LoginTests.test_login_with_mobile | B59: accounts | C59: Integration | D59: LoginTests | E59: Login with mobile | F59: TC-ACC-05 | G59: python manage.py test apps.accounts.tests.LoginTests.test_login_with_mobile --settings=config.settings.test
A60: apps.accounts.tests.LoginTests.test_wrong_password | B60: accounts | C60: Integration | D60: LoginTests | E60: Wrong password | G60: python manage.py test apps.accounts.tests.LoginTests.test_wrong_password --settings=config.settings.test
A61: apps.accounts.tests.HealthTests.test_health | B61: accounts | C61: Integration | D61: HealthTests | E61: Health | F61: TC-SET-1 | G61: python manage.py test apps.accounts.tests.HealthTests.test_health --settings=config.settings.test
A62: apps.accounts.tests.HealthTests.test_health_is_503_when_the_database_is_unreachable | B62: accounts | C62: Integration | D62: HealthTests | E62: Render must see a failing status, or a broken deploy would receive traffic. | F62: TC-SET-1 | G62: python manage.py test apps.accounts.tests.HealthTests.test_health_is_503_when_the_database_is_unreachable --settings=config.settings.test
A63: apps.accounts.tests.SeedTests.test_seed_is_idempotent | B63: accounts | C63: Integration | D63: SeedTests | E63: Seed is idempotent | G63: python manage.py test apps.accounts.tests.SeedTests.test_seed_is_idempotent --settings=config.settings.test
A64: apps.accounts.tests.GuardianConsentTests.test_new_student_awaits_consent | B64: accounts | C64: Integration | D64: GuardianConsentTests | E64: New student awaits consent | G64: python manage.py test apps.accounts.tests.GuardianConsentTests.test_new_student_awaits_consent --settings=config.settings.test
A65: apps.accounts.tests.GuardianConsentTests.test_only_one_active_primary_guardian | B65: accounts | C65: Integration | D65: GuardianConsentTests | E65: Only one active primary guardian | F65: TC-CON-09 | G65: python manage.py test apps.accounts.tests.GuardianConsentTests.test_only_one_active_primary_guardian --settings=config.settings.test
A66: apps.accounts.tests.GuardianConsentTests.test_ended_link_frees_primary_slot | B66: accounts | C66: Integration | D66: GuardianConsentTests | E66: Ended link frees primary slot | G66: python manage.py test apps.accounts.tests.GuardianConsentTests.test_ended_link_frees_primary_slot --settings=config.settings.test
A67: apps.accounts.tests.GuardianConsentTests.test_consent_record_active_until_withdrawn | B67: accounts | C67: Integration | D67: GuardianConsentTests | E67: Consent record active until withdrawn | F67: TC-SEC-06 | G67: python manage.py test apps.accounts.tests.GuardianConsentTests.test_consent_record_active_until_withdrawn --settings=config.settings.test
A68: apps.accounts.tests.TokenAndApprovalTests.test_link_token_stored_only_as_hash | B68: accounts | C68: Integration | D68: TokenAndApprovalTests | E68: Link token stored only as hash | F68: TC-SEC-05 | G68: python manage.py test apps.accounts.tests.TokenAndApprovalTests.test_link_token_stored_only_as_hash --settings=config.settings.test
A69: apps.accounts.tests.TokenAndApprovalTests.test_otp_is_six_digits | B69: accounts | C69: Integration | D69: TokenAndApprovalTests | E69: Otp is six digits | G69: python manage.py test apps.accounts.tests.TokenAndApprovalTests.test_otp_is_six_digits --settings=config.settings.test
A70: apps.accounts.tests.TokenAndApprovalTests.test_approval_request_expiry | B70: accounts | C70: Integration | D70: TokenAndApprovalTests | E70: Approval request expiry | G70: python manage.py test apps.accounts.tests.TokenAndApprovalTests.test_approval_request_expiry --settings=config.settings.test
A71: apps.accounts.tests.RoleTests.test_scoped_role | B71: accounts | C71: Integration | D71: RoleTests | E71: Scoped role | G71: python manage.py test apps.accounts.tests.RoleTests.test_scoped_role --settings=config.settings.test
A72: apps.accounts.tests.RoleTests.test_revoked_role | B72: accounts | C72: Integration | D72: RoleTests | E72: Revoked role | G72: python manage.py test apps.accounts.tests.RoleTests.test_revoked_role --settings=config.settings.test
A73: apps.accounts.tests.RoleTests.test_no_duplicate_active_grant | B73: accounts | C73: Integration | D73: RoleTests | E73: No duplicate active grant | F73: TC-ADM-07 | G73: python manage.py test apps.accounts.tests.RoleTests.test_no_duplicate_active_grant --settings=config.settings.test
A74: apps.accounts.tests.DevToolsAreLockedTests.test_seed_test_accounts_refuses_without_dev_flags | B74: accounts | C74: Integration | D74: DevToolsAreLockedTests | E74: Seed test accounts refuses without dev flags | F74: TC-SEC-11 | G74: python manage.py test apps.accounts.tests.DevToolsAreLockedTests.test_seed_test_accounts_refuses_without_dev_flags --settings=config.settings.test
A75: apps.accounts.tests.DevToolsAreLockedTests.test_dev_outbox_not_mounted_when_debug_off | B75: accounts | C75: Integration | D75: DevToolsAreLockedTests | E75: Dev outbox not mounted when debug off | F75: TC-SEC-11 | G75: python manage.py test apps.accounts.tests.DevToolsAreLockedTests.test_dev_outbox_not_mounted_when_debug_off --settings=config.settings.test
A76: apps.catalogue.test_queries.PaginateConcatenatedTests.test_page_inside_first_source | B76: catalogue | C76: Performance (query budget) | D76: PaginateConcatenatedTests | E76: Page inside first source | G76: python manage.py test apps.catalogue.test_queries.PaginateConcatenatedTests.test_page_inside_first_source --settings=config.settings.test
A77: apps.catalogue.test_queries.PaginateConcatenatedTests.test_page_spanning_both_sources | B77: catalogue | C77: Performance (query budget) | D77: PaginateConcatenatedTests | E77: Page spanning both sources | G77: python manage.py test apps.catalogue.test_queries.PaginateConcatenatedTests.test_page_spanning_both_sources --settings=config.settings.test
A78: apps.catalogue.test_queries.PaginateConcatenatedTests.test_page_inside_second_source | B78: catalogue | C78: Performance (query budget) | D78: PaginateConcatenatedTests | E78: Page inside second source | G78: python manage.py test apps.catalogue.test_queries.PaginateConcatenatedTests.test_page_inside_second_source --settings=config.settings.test
A79: apps.catalogue.test_queries.PaginateConcatenatedTests.test_page_past_the_end | B79: catalogue | C79: Performance (query budget) | D79: PaginateConcatenatedTests | E79: Page past the end | G79: python manage.py test apps.catalogue.test_queries.PaginateConcatenatedTests.test_page_past_the_end --settings=config.settings.test
A80: apps.catalogue.test_queries.PaginateConcatenatedTests.test_no_sources | B80: catalogue | C80: Performance (query budget) | D80: PaginateConcatenatedTests | E80: No sources | G80: python manage.py test apps.catalogue.test_queries.PaginateConcatenatedTests.test_no_sources --settings=config.settings.test
A81: apps.catalogue.test_queries.CatalogueQueryTests.test_items_are_paginated_in_the_database | B81: catalogue | C81: Performance (query budget) | D81: CatalogueQueryTests | E81: Items are paginated in the database | F81: TC-CAT-04 | G81: python manage.py test apps.catalogue.test_queries.CatalogueQueryTests.test_items_are_paginated_in_the_database --settings=config.settings.test
A82: apps.catalogue.test_queries.CatalogueQueryTests.test_items_spill_from_courses_into_programmes | B82: catalogue | C82: Performance (query budget) | D82: CatalogueQueryTests | E82: Items spill from courses into programmes | G82: python manage.py test apps.catalogue.test_queries.CatalogueQueryTests.test_items_spill_from_courses_into_programmes --settings=config.settings.test
A83: apps.catalogue.test_queries.CatalogueQueryTests.test_items_query_count_is_constant | B83: catalogue | C83: Performance (query budget) | D83: CatalogueQueryTests | E83: Items query count is constant | G83: python manage.py test apps.catalogue.test_queries.CatalogueQueryTests.test_items_query_count_is_constant --settings=config.settings.test
A84: apps.catalogue.test_queries.CatalogueQueryTests.test_items_with_board_filter_query_count_is_constant | B84: catalogue | C84: Performance (query budget) | D84: CatalogueQueryTests | E84: Items with board filter query count is constant | G84: python manage.py test apps.catalogue.test_queries.CatalogueQueryTests.test_items_with_board_filter_query_count_is_constant --settings=config.settings.test
A85: apps.catalogue.test_queries.CatalogueQueryTests.test_facets_query_count_is_constant | B85: catalogue | C85: Performance (query budget) | D85: CatalogueQueryTests | E85: Facets query count is constant | G85: python manage.py test apps.catalogue.test_queries.CatalogueQueryTests.test_facets_query_count_is_constant --settings=config.settings.test
A86: apps.catalogue.test_queries.CatalogueQueryTests.test_course_detail_query_count_is_constant | B86: catalogue | C86: Performance (query budget) | D86: CatalogueQueryTests | E86: Course detail query count is constant | G86: python manage.py test apps.catalogue.test_queries.CatalogueQueryTests.test_course_detail_query_count_is_constant --settings=config.settings.test
A87: apps.catalogue.test_queries.CatalogueQueryTests.test_course_detail_marks_lessons_without_content | B87: catalogue | C87: Performance (query budget) | D87: CatalogueQueryTests | E87: Course detail marks lessons without content | G87: python manage.py test apps.catalogue.test_queries.CatalogueQueryTests.test_course_detail_marks_lessons_without_content --settings=config.settings.test
A88: apps.catalogue.test_queries.CatalogueQueryTests.test_programme_detail_query_count_is_constant | B88: catalogue | C88: Performance (query budget) | D88: CatalogueQueryTests | E88: Programme detail query count is constant | G88: python manage.py test apps.catalogue.test_queries.CatalogueQueryTests.test_programme_detail_query_count_is_constant --settings=config.settings.test
A89: apps.catalogue.tests.CatalogueApiTests.test_facets | B89: catalogue | C89: Integration | D89: CatalogueApiTests | E89: Facets | F89: TC-CAT-01 | G89: python manage.py test apps.catalogue.tests.CatalogueApiTests.test_facets --settings=config.settings.test
A90: apps.catalogue.tests.CatalogueApiTests.test_items_lists_published_only | B90: catalogue | C90: Integration | D90: CatalogueApiTests | E90: Items lists published only | F90: TC-CAT-02 | G90: python manage.py test apps.catalogue.tests.CatalogueApiTests.test_items_lists_published_only --settings=config.settings.test
A91: apps.catalogue.tests.CatalogueApiTests.test_board_filter_keeps_board_independent_courses | B91: catalogue | C91: Integration | D91: CatalogueApiTests | E91: Board filter keeps board independent courses | F91: TC-CAT-03 | G91: python manage.py test apps.catalogue.tests.CatalogueApiTests.test_board_filter_keeps_board_independent_courses --settings=config.settings.test
A92: apps.catalogue.tests.CatalogueApiTests.test_class_filter | B92: catalogue | C92: Integration | D92: CatalogueApiTests | E92: Class filter | F92: TC-CAT-03 | G92: python manage.py test apps.catalogue.tests.CatalogueApiTests.test_class_filter --settings=config.settings.test
A93: apps.catalogue.tests.CatalogueApiTests.test_pagination | B93: catalogue | C93: Integration | D93: CatalogueApiTests | E93: Pagination | F93: TC-CAT-04 | G93: python manage.py test apps.catalogue.tests.CatalogueApiTests.test_pagination --settings=config.settings.test
A94: apps.catalogue.tests.CatalogueApiTests.test_course_detail | B94: catalogue | C94: Integration | D94: CatalogueApiTests | E94: Course detail | F94: TC-CAT-05 | G94: python manage.py test apps.catalogue.tests.CatalogueApiTests.test_course_detail --settings=config.settings.test
A95: apps.catalogue.tests.CatalogueApiTests.test_draft_course_is_404 | B95: catalogue | C95: Integration | D95: CatalogueApiTests | E95: Draft course is 404 | F95: TC-CAT-06 | G95: python manage.py test apps.catalogue.tests.CatalogueApiTests.test_draft_course_is_404 --settings=config.settings.test
A96: apps.catalogue.tests.CatalogueApiTests.test_programme_detail | B96: catalogue | C96: Integration | D96: CatalogueApiTests | E96: Programme detail | F96: TC-CAT-07 | G96: python manage.py test apps.catalogue.tests.CatalogueApiTests.test_programme_detail --settings=config.settings.test
A97: apps.catalogue.tests.CatalogueApiTests.test_free_lesson_preview | B97: catalogue | C97: Integration | D97: CatalogueApiTests | E97: Free lesson preview | F97: TC-CAT-08 | G97: python manage.py test apps.catalogue.tests.CatalogueApiTests.test_free_lesson_preview --settings=config.settings.test
A98: apps.catalogue.tests.CatalogueApiTests.test_paid_lesson_preview_is_blocked | B98: catalogue | C98: Integration | D98: CatalogueApiTests | E98: Paid lesson preview is blocked | F98: TC-CAT-09 | G98: python manage.py test apps.catalogue.tests.CatalogueApiTests.test_paid_lesson_preview_is_blocked --settings=config.settings.test
A99: apps.catalogue.tests.CatalogueApiTests.test_demo_seed_is_idempotent | B99: catalogue | C99: Integration | D99: CatalogueApiTests | E99: Demo seed is idempotent | G99: python manage.py test apps.catalogue.tests.CatalogueApiTests.test_demo_seed_is_idempotent --settings=config.settings.test
A100: apps.catalogue.tests.ContentVersionTests.test_publishing_archives_previous | B100: catalogue | C100: Integration | D100: ContentVersionTests | E100: Publishing archives previous | F100: TC-ADM-04 | G100: python manage.py test apps.catalogue.tests.ContentVersionTests.test_publishing_archives_previous --settings=config.settings.test
A101: apps.catalogue.tests.ContentVersionTests.test_only_approved_can_be_published | B101: catalogue | C101: Integration | D101: ContentVersionTests | E101: Only approved can be published | F101: TC-ADM-05 | G101: python manage.py test apps.catalogue.tests.ContentVersionTests.test_only_approved_can_be_published --settings=config.settings.test
A102: apps.catalogue.tests.ContentVersionTests.test_reviewer_cannot_be_author | B102: catalogue | C102: Integration | D102: ContentVersionTests | E102: Reviewer cannot be author | F102: TC-SEC-09 | G102: python manage.py test apps.catalogue.tests.ContentVersionTests.test_reviewer_cannot_be_author --settings=config.settings.test
...

Sheet Smoke checks
A1: Mode | B1: Check | C1: What it checks | D1: Command (from backend/)
A2: Hosted (read-only) | B2: hosted:H0 | C2: site reachable | D2: python qa/smoke_test.py --hosted --base <site URL>
A3: Hosted (read-only) | B3: hosted:H1 | C3: healthy and database reachable | D3: python qa/smoke_test.py --hosted --base <site URL>
A4: Hosted (read-only) | B4: hosted:H2 | C4: HSTS header present | D4: python qa/smoke_test.py --hosted --base <site URL>
A5: Hosted (read-only) | B5: hosted:H3 | C5: nosniff header present | D5: python qa/smoke_test.py --hosted --base <site URL>
A6: Hosted (read-only) | B6: hosted:H4 | C6: plain HTTP redirects to HTTPS | D6: python qa/smoke_test.py --hosted --base <site URL>
A7: Hosted (read-only) | B7: hosted:H5 | C7: root page points to the API docs | D7: python qa/smoke_test.py --hosted --base <site URL>
A8: Hosted (read-only) | B8: hosted:H6 | C8: CSRF cookie is Secure | D8: python qa/smoke_test.py --hosted --base <site URL>
A9: Hosted (read-only) | B9: hosted:C1 | C9: catalogue lists AI Foundations | D9: python qa/smoke_test.py --hosted --base <site URL>
A10: Hosted (read-only) | B10: hosted:C2 | C10: course has lessons and skills | D10: python qa/smoke_test.py --hosted --base <site URL>
A11: Hosted (read-only) | B11: hosted:C3 | C11: course has a free lesson | D11: python qa/smoke_test.py --hosted --base <site URL>
A12: Hosted (read-only) | B12: hosted:C4 | C12: free lesson preview readable without login | D12: python qa/smoke_test.py --hosted --base <site URL>
... A43: Local journey | B43: smoke:X2 | C43: unknown course is 404 | D43: python qa/smoke_test.py

Sheet Traceability
A1: Requirement | B1: Area | C1: Requirement text | D1: Build status | E1: Manual cases | F1: # manual | G1: # automated | H1: Coverage
A2: FR-ACC-1 | B2: ACC | C2: Sign-up and login with email or mobile (10-digit Indian numbers accepted and stored as +91…) | D2: Implemented | E2: TC-ACC-01, TC-ACC-03, TC-ACC-04, TC-ACC-05, TC-DEMO-01 | F2: 5 | G2: 8 | H2: =IF(F2=0,"No manual case",IF(G2=0,"Manual only","Manual + automated")) -> Manual + automated
A3: FR-ACC-2 | B3: ACC | C3: Contact verification and password reset by 6-digit one-time code (10-minute expiry, 5 attempts, 5 codes / 10 min) | D3: Implemented | E3: TC-ACC-02, TC-ACC-08, TC-ACC-09 | F3: 3 | G3: 4 | H3: =IF(F3=0,"No manual case",IF(G3=0,"Manual only","Manual + automated")) -> Manual + automated
A4: FR-ACC-3 | B4: ACC | C4: Codes are never sent to unregistered contacts, so the API doesn't reveal who is registered | D4: Implemented | E4: TC-ACC-10, TC-SEC-10, TC-SEC-14 | F4: 3 | G4: 3 | H4: =IF(F4=0,"No manual case",IF(G4=0,"Manual only","Manual + automated")) -> Manual + automated
A5: FR-ACC-4 | B5: ACC | C5: Student accounts start `awaiting_consent`; parent approves via a hashed, 7-day link | D5: Implemented | E5: TC-ACC-01, TC-CON-01, TC-CON-02 | F5: 3 | G5: 6 | H5: =IF(F5=0,"No manual case",IF(G5=0,"Manual only","Manual + automated")) -> Manual + automated
A6: FR-ACC-5 | B6: ACC | C6: Consent records store the exact consent-text version, time and IP | D6: Implemented | E6: TC-CON-02, TC-SEC-06 | F6: 2 | G6: 4 | H6: =IF(F6=0,"No manual case",IF(G6=0,"Manual only","Manual + automated")) -> Manual + automated
A7: FR-ACC-6 | B7: ACC | C7: One active primary guardian per student (v1) | D7: Implemented | E7: TC-CON-09 | F7: 1 | G7: 1 | H7: =IF(F7=0,"No manual case",IF(G7=0,"Manual only","Manual + automated")) -> Manual + automated
A8: FR-ACC-7 | B8: ACC | C8: Withdrawal pauses the student immediately; restore reactivates | D8: Implemented | E8: TC-CON-11 | F8: 1 | G8: 5 | H8: =IF(F8=0,"No manual case",IF(G8=0,"Manual only","Manual + automated")) -> Manual + automated
A9: FR-ACC-8 | B9: ACC | C9: Unapproved student accounts deleted after 30 days; data deleted 30 days after withdrawal | D9: Planned (scheduled job) | F9: 0 | G9: 0 | H9: =IF(F9=0,"No manual case",IF(G9=0,"Manual only","Manual + automated")) -> No manual case
A10: FR-ACC-9 | B10: ACC | C10: Roles (author, reviewer, batch teacher, curriculum lead, operations, super admin) scoped by subject and class | D10: Implemented (model; publishing and role management enforced) | E10: TC-ADM-07 | F10: 1 | G10: 2 | H10: =IF(F10=0,"No manual case",IF(G10=0,"Manual only","Manual + automated")) -> Manual + automated
A11: FR-CAT-1 | B11: CAT | C11: Discipline → Subject → Course → Module → Lesson; skills with prerequisites; board chapter mappings | D11: Implemented | F11: 0 | G11: 0 | H11: =IF(F11=0,"No manual case",IF(G11=0,"Manual only","Manual + automated")) -> No manual case
A12: FR-CAT-2 | B12: CAT | C12: Public list filtered by class, board, subject and stage; board-independent courses always match | D12: Implemented | E12: TC-CAT-01, TC-CAT-02, TC-CAT-03, TC-DEMO-06 | F12: 4 | G12: 7 | H12: =IF(F12=0,"No manual case",IF(G12=0,"Manual only","Manual + automated")) -> Manual + automated
A13: FR-CAT-3 | B13: CAT | C13: First module of a course readable free (without AI tutor) | D13: Implemented | E13: TC-CAT-08, TC-CAT-09 | F13: 2 | G13: 3 | H13: =IF(F13=0,"No manual case",IF(G13=0,"Manual only","Manual + automated")) -> Manual + automated
A14: FR-CON-1 | B14: CON | C14: Every lesson and question edit is a new version; published versions are immutable | D14: Implemented | E14: TC-SEC-08 | F14: 1 | G14: 2 | H14: =IF(F14=0,"No manual case",IF(G14=0,"Manual only","Manual + automated")) -> Manual + automated
A15: FR-CON-2 | B15: CON | C15: One published version per lesson/question; reviewer ≠ author (database-enforced) | D15: Implemented | E15: TC-DEMO-11, TC-SEC-09 | F15: 2 | G15: 2 | H15: =IF(F15=0,"No manual case",IF(G15=0,"Manual only","Manual + automated")) -> Manual + automated
A16: FR-CON-3 | B16: CON | C16: Publishing archives the previous version and re-indexes the lesson for the tutor | D16: Archive implemented; re-index planned | E16: TC-ADM-04, TC-ADM-09, TC-DEMO-07, TC-SEC-17 | F16: 4 | G16: 7 | H16: =IF(F16=0,"No manual case",IF(G16=0,"Manual only","Manual + automated")) -> Manual + automated
A17: FR-LRN-1 | B17: LRN | C17: Lessons, quizzes and the tutor require an active (consented) student account | D17: Implemented | E17: TC-DEMO-02, TC-LRN-01, TC-LRN-02 | F17: 3 | G17: 6 | H17: =IF(F17=0,"No manual case",IF(G17=0,"Manual only","Manual + automated")) -> Manual + automated
A18: FR-LRN-2 | B18: LRN | C18: Paid lessons require an active entitlement to the course or a programme containing it | D18: Implemented | E18: TC-DEMO-03, TC-LRN-03, TC-LRN-04 | F18: 3 | G18: 3 | H18: =IF(F18=0,"No manual case",IF(G18=0,"Manual only","Manual + automated")) -> Manual + automated
A19: FR-LRN-3 | B19: LRN | C19: Quiz answers are never sent to the client before answering; each answer references the exact question version shown | D19: Implemented | E19: TC-QZ-01 | F19: 1 | G19: 2 | H19: =IF(F19=0,"No manual case",IF(G19=0,"Manual only","Manual + automated")) -> Manual + automated
A20: FR-LRN-4 | B20: LRN | C20: Mastery per skill: `score ← score + 0.35 × (credit − score)`; each hint removes 25% of credit; *mastered* needs score ≥ 0.75 and ≥ 3 answers | D20: Implemented | E20: TC-QZ-03, TC-MAS-01, TC-MAS-02 | F20: 3 | G20: 4 | H20: =IF(F20=0,"No manual case",IF(G20=0,"Manual only","Manual + automated")) -> Manual + automated
A21: FR-LRN-5 | B21: LRN | C21: Every mastery change is logged with the answer that caused it | D21: Implemented | E21: TC-DEMO-04, TC-MAS-01 | F21: 2 | G21: 3 | H21: =IF(F21=0,"No manual case",IF(G21=0,"Manual only","Manual + automated")) -> Manual + automated
A22: FR-LRN-6 | B22: LRN | C22: Course complete = all lessons finished and every taught skill at least *developing* | D22: Implemented | E22: TC-DEMO-04, TC-MAS-03 | F22: 2 | G22: 3 | H22: =IF(F22=0,"No manual case",IF(G22=0,"Manual only","Manual + automated")) -> Manual + automated
A23: FR-LRN-7 | B23: LRN | C23: Today: next unfinished lesson, weakest-skill review, streak counted in IST | D23: Implemented | E23: TC-TDY-01 | F23: 1 | G23: 2 | H23: =IF(F23=0,"No manual case",IF(G23=0,"Manual only","Manual + automated")) -> Manual + automated
A24: FR-LRN-8 | B24: LRN | C24: Adaptive warm-up check using skill prerequisites | D24: Planned | F24: 0 | G24: 0 | H24: =IF(F24=0,"No manual case",IF(G24=0,"Manual only","Manual + automated")) -> No manual case
A25: FR-AI-1 | B25: AI | C25: Tutor modes Explain / Socratic / Hint, grounded in published lesson content with cited sections | D25: Planned | F25: 0 | G25: 0 | H25: =IF(F25=0,"No manual case",IF(G25=0,"Manual only","Manual + automated")) -> No manual case
A26: FR-AI-2 | B26: AI | C26: Daily message limit per student (default 50, admin-adjustable) | D26: Planned | F26: 0 | G26: 0 | H26: =IF(F26=0,"No manual case",IF(G26=0,"Manual only","Manual + automated")) -> No manual case
A27: FR-AI-3 | B27: AI | C27: Safety check on every message; flags routed to operations | D27: Planned | F27: 0 | G27: 0 | H27: =IF(F27=0,"No manual case",IF(G27=0,"Manual only","Manual + automated")) -> No manual case
A28: FR-COM-1 | B28: COM | C28: Razorpay checkout; entitlement created only from a signature-verified webhook | D28: Planned | F28: 0 | G28: 0 | H28: =IF(F28=0,"No manual case",IF(G28=0,"Manual only","Manual + automated")) -> No manual case
A29: FR-COM-2 | B29: COM | C29: Idempotency keys on order creation | D29: Planned | F29: 0 | G29: 0 | H29: =IF(F29=0,"No manual case",IF(G29=0,"Manual only","Manual + automated")) -> No manual case
A30: FR-BAT-1 | B30: BAT | C30: Batches with class, board, mode, city, centre, teacher, seats, price; sessions with meeting links; attendance | D30: Planned | F30: 0 | G30: 0 | H30: =IF(F30=0,"No manual case",IF(G30=0,"Manual only","Manual + automated")) -> No manual case
A31: FR-OPS-1 | B31: OPS | C31: Append-only audit log of consent, role, publishing, refund and suspension changes | D31: Implemented (consent, publishing, roles) | E31: TC-SEC-07 | F31: 1 | G31: 1 | H31: =IF(F31=0,"No manual case",IF(G31=0,"Manual only","Manual + automated")) -> Manual + automated
A32: NFR-SEC-1 | B32: Security | C32: Server-side authorization on every endpoint; the browser talks only to Django | D32: — | E32: TC-HOST-03, TC-SEC-01 | F32: 2 | G32: 4 | H32: =IF(F32=0,"No manual case",IF(G32=0,"Manual only","Manual + automated")) -> Manual + automated
A33: NFR-SEC-2 | B33: Security | C33: Session cookies HttpOnly, Secure (prod), SameSite=Lax; CSRF on state-changing requests | D33: — | E33: TC-SET-3, TC-HOST-04 | F33: 2 | G33: 3 | H33: =IF(F33=0,"No manual case",IF(G33=0,"Manual only","Manual + automated")) -> Manual + automated
A34: NFR-SEC-3 | B34: Security | C34: Secrets only in environment variables; link tokens and one-time codes stored as SHA-256 hashes | D34: — | E34: TC-SEC-05 | F34: 1 | G34: 1 | H34: =IF(F34=0,"No manual case",IF(G34=0,"Manual only","Manual + automated")) -> Manual + automated
A35: NFR-SEC-4 | B35: Security | C35: Brute-force protection: rate limits on login, sign-up, one-time codes and consent links; per-account login lockout | D35: — | E35: TC-SEC-13, TC-SEC-15, TC-SEC-16 | F35: 3 | G35: 5 | H35: =IF(F35=0,"No manual case",IF(G35=0,"Manual only","Manual + automated")) -> Manual + automated
A36: NFR-SEC-5 | B36: Security | C36: Least privilege in the back office: publishing, role grants and admin access decided by role grants, not staff status | D36: — | E36: TC-DEMO-08, TC-DEMO-09, TC-DEMO-10, TC-SEC-18 | F36: 4 | G36: 6 | H36: =IF(F36=0,"No manual case",IF(G36=0,"Manual only","Manual + automated")) -> Manual + automated
A37: NFR-PRIV-1 | B37: Privacy | C37: Data minimisation (class, not date of birth); AI service receives a pseudonymous learner reference only | D37: — | E37: TC-SEC-12 | F37: 1 | G37: 0 | H37: =IF(F37=0,"No manual case",IF(G37=0,"Manual only","Manual + automated")) -> Manual only
A38: NFR-PRIV-2 | B38: Privacy | C38: Parent can withdraw consent, export and delete the child's data | D38: — | F38: 0 | G38: 0 | H38: =IF(F38=0,"No manual case",IF(G38=0,"Manual only","Manual + automated")) -> No manual case
A39: NFR-PERF-1 | B39: Performance | C39: API p95 < 300 ms for non-AI endpoints at launch load; tutor first token < 3 s | D39: — | F39: 0 | G39: 0 | H39: =IF(F39=0,"No manual case",IF(G39=0,"Manual only","Manual + automated")) -> No manual case
A40: NFR-AVAIL-1 | B40: Availability | C40: Health endpoint for platform checks; database backups with a tested restore before launch | D40: — | E40: TC-SET-1, TC-HOST-01 | F40: 2 | G40: 6 | H40: =IF(F40=0,"No manual case",IF(G40=0,"Manual only","Manual + automated")) -> Manual + automated
A41: NFR-QUAL-1 | B41: Quality | C41: Every feature ships with tests; CI (lint incl. security rules, migrations check, deploy check, dependency audit, tests with ≥ 90% branch coverage) must pass before merge | D41: — | F41: 0 | G41: 0 | H41: =IF(F41=0,"No manual case",IF(G41=0,"Manual only","Manual + automated")) -> No manual case
A42: NFR-PERF-2 | B42: Performance | C42: Query count per request independent of data size (no N+1); lists paginated in the database | D42: — | F42: 0 | G42: 0 | H42: =IF(F42=0,"No manual case",IF(G42=0,"Manual only","Manual + automated")) -> No manual case
A43: NFR-A11Y-1 | B43: Accessibility | C43: Web app meets WCAG 2.1 AA for keyboard use, contrast and screen readers | D43: — | F43: 0 | G43: 0 | H43: =IF(F43=0,"No manual case",IF(G43=0,"Manual only","Manual + automated")) -> No manual case
A44: NFR-COST-1 | B44: Cost | C44: AI cost logged per message; cheaper models for simple tasks; per-student daily limits | D44: — | F44: 0 | G44: 0 | H44: =IF(F44=0,"No manual case",IF(G44=0,"Manual only","Manual + automated")) -> No manual case
A45: NFR-TIME-1 | B45: Time | C45: Stored in UTC; shown and "today" computed in IST (Asia/Kolkata) | D45: — | E45: TC-DEMO-05, TC-TDY-02 | F45: 2 | G45: 4 | H45: =IF(F45=0,"No manual case",IF(G45=0,"Manual only","Manual + automated")) -> Manual + automated

Sheet Demo accounts
A1: Key | B1: Name | C1: Mobile | D1: Email | E1: Role / state | F1: Use it to test
A2: parent | B2: Test Parent | C2: 9000000001 | D2: parent@test.tutor | E2: Parent of Asha, Esha, Kabir | F2: Parent views, withdraw/restore consent, add a child
A3: priya | B3: Priya Nair | C3: 9000000011 | D3: priya@test.tutor | E3: Parent of Meera, Zoya, Ishaan | F3: Several children, different classes
A4: rahul | B4: Rahul Das | C4: 9000000012 | D4: rahul@test.tutor | E4: Wasim's parent; approval pending | F4: Approval flow (local: link in the dev outbox)
A5: farhan | B5: Farhan Ali | C5: 9000000013 | D5: farhan@test.tutor | E5: Withdrew consent for Rohan | F5: Restoring consent
A6: student_active | B6: Asha Active | C6: 9000000002 | D6: asha@test.tutor | E6: Class 8 CBSE, active, nothing bought | F6: Free lessons only; paid lessons refused
A7: student_enrolled | B7: Esha Enrolled | C7: 9000000003 | D7: esha@test.tutor | E7: Class 8 CBSE, AI Foundations | F7: One quiz taken; continue the course
A8: student_waiting | B8: Wasim Waiting | C8: 9000000004 | D8: wasim@test.tutor | E8: Class 8, awaiting consent | F8: Everything except browsing is blocked
A9: kabir | B9: Kabir Sen | C9: 9000000021 | D9: kabir@test.tutor | E9: Class 8 CBSE, Class 8 Foundation programme | F9: Rich record: AI Foundations completed, 7 quizzes, weak on inverses (review item)
A10: meera | B10: Meera Nair | C10: 9000000022 | D10: meera@test.tutor | E10: Class 11 ICSE, Physics 11 | F10: Mid-course, 3-day streak
A11: zoya | B11: Zoya Nair | C11: 9000000023 | D11: zoya@test.tutor | E11: Class 6 CBSE, Class 6 Maths Start | F11: 5-day streak, a quiz retake
A12: rohan | B12: Rohan Ali | C12: 9000000024 | D12: rohan@test.tutor | E12: Class 8 ICSE, paused (consent withdrawn) | F12: Blocked with `consent_required`; history kept
... A20: omar | B20: Omar Sheikh | C20: 9000000043 | D20: omar@test.tutor | E20: Operations | F20: Can: Look up users, grant enrolments (entitlements). Cannot: Publish anything, grant roles

Sheet Bug log
A1: Bug ID | B1: TC ID | C1: Title | D1: Severity | E1: Environment | F1: Steps to reproduce | G1: Expected | H1: Actual | I1: Reported by | J1: Reported on | K1: Status | L1: Notes
A2: BUG-001 | B2: TC-QZ-06 | C2: Answering twice returns 500 instead of 409 | D2: High | E2: Local | F2: Start quiz; answer position 1; answer position 1 again | G2: 409 conflict | H2: 500 server error | I2: Tester name | J2: 46296 | K2: Open | L2: Example row: replace or delete
